adivina.py
setup.py
ADIVINA_EL_NUMERO.egg-info/PKG-INFO
ADIVINA_EL_NUMERO.egg-info/SOURCES.txt
ADIVINA_EL_NUMERO.egg-info/dependency_links.txt
ADIVINA_EL_NUMERO.egg-info/top_level.txt