Metadata-Version: 1.0
Name: ADIVINA_EL_NUMERO
Version: 0.1
Summary: Ejemplo del funcionamiento de distutils
Home-page: http://mundogeek.net/tutorial-python/
Author: JULIAN RODRIGUEZ
Author-email: julianrodri11@gmail
License: GPL
Platform: UNKNOWN
